README.md
setup.cfg
setup.py
darklyrics/__init__.py
darklyrics/darklyrics.py
darklyrics.egg-info/PKG-INFO
darklyrics.egg-info/SOURCES.txt
darklyrics.egg-info/dependency_links.txt
darklyrics.egg-info/requires.txt
darklyrics.egg-info/top_level.txt