Metadata-Version: 1.0
Name: darklyrics
Version: 0.1.5
Summary: Darklyrics API for song lyrics
Home-page: http://github.com/res0nance/darklyrics
Author: Raihaan
Author-email: raihaanhimself@gmail.com
License: MIT
Keywords: darklyrics lyric lyrics song api
Platform: UNKNOWN
